LICENSE
README.md
setup.cfg
setup.py
pyautodb/__init__.py
pyautodb/client.py
pyautodb/common.py
pyautodb/exceptions.py
pyautodb.egg-info/PKG-INFO
pyautodb.egg-info/SOURCES.txt
pyautodb.egg-info/dependency_links.txt
pyautodb.egg-info/requires.txt
pyautodb.egg-info/top_level.txt