Metadata-Version: 2.1
Name: pyautodb
Version: 0.1
Summary: A library that combines multiple document based databases.
Home-page: https://github.com/bossauh/pyautodb
Download-URL: https://github.com/bossauh/pyautodb/archive/refs/tags/v_01.tar.gz
Author: Philippe Mathew
Author-email: philmattdev@gmail.com
License: MIT
Platform: UNKNOWN
License-File: LICENSE
